gen_form_model/__init__.py
gen_form_model/py.typed
gen_form_model/conf/gen_form_model.cfg
gen_form_model/conf/gen_form_model_util.cfg
gen_form_model/conf/project.yaml
gen_form_model/conf/template/django.template
gen_form_model/conf/template/flask.template
gen_form_model/log/gen_form_model.log
gen_form_model/pro/__init__.py
gen_form_model/pro/read_template.py
gen_form_model/pro/write_template.py
usr/local/bin/gen_form_model_run.py
gen_form_model-1.6.7.dist-info/LICENSE
gen_form_model-1.6.7.dist-info/METADATA
gen_form_model-1.6.7.dist-info/WHEEL
gen_form_model-1.6.7.dist-info/top_level.txt
gen_form_model-1.6.7.dist-info/RECORD
