Metadata-Version: 2.1
Name: gen_form_model
Version: 1.6.7
Summary: Form model based on Django, Flask
Home-page: https://vroncevic.github.io/gen_form_model/
Author: Vladimir Roncevic
Author-email: elektron.ronca@gmail.com
License: GPL 2024 Free software to use and distributed it.
Keywords: form model,django form,flask form
Platform: POSIX
Classifier: Programming Language :: Python :: 3.10
Classifier: Programming Language :: Python :: 3.11
Classifier: License :: OSI Approved :: GNU Lesser General Public License v2 (LGPLv2)
Classifier: License :: OSI Approved :: GNU Lesser General Public License v2 or later (LGPLv2+)
Classifier: License :: OSI Approved :: GNU Lesser General Public License v3 (LGPLv3)
Classifier: License :: OSI Approved :: GNU Lesser General Public License v3 or later (LGPLv3+)
Classifier: License :: OSI Approved :: GNU Library or Lesser General Public License (LGPL)
Requires-Python: >=3.10
License-File: LICENSE
Requires-Dist: ats-utilities
